{
  "total_samples": 1,
  "successful": 0,
  "failed": 1,
  "error_rate": 100,
  "average_ms": 954,
  "min_ms": 954,
  "max_ms": 954,
  "p50_ms": 954,
  "p90_ms": 954,
  "p95_ms": 954,
  "p99_ms": 954,
  "endpoints": {
    "websocket ping": {
      "count": 1,
      "failed": 1,
      "average_ms": 954,
      "p95_ms": 954
    }
  },
  "thresholds": [
    {
      "name": "error_rate_lt",
      "limit": 100,
      "actual": 100,
      "passed": false
    },
    {
      "name": "p95_ms_lt",
      "limit": 2000,
      "actual": 954,
      "passed": true
    }
  ]
}
